azure/mgmt/trafficmanager/__init__.py
azure/mgmt/trafficmanager/_configuration.py
azure/mgmt/trafficmanager/_patch.py
azure/mgmt/trafficmanager/_traffic_manager_management_client.py
azure/mgmt/trafficmanager/_vendor.py
azure/mgmt/trafficmanager/_version.py
azure/mgmt/trafficmanager/aio/__init__.py
azure/mgmt/trafficmanager/aio/_configuration.py
azure/mgmt/trafficmanager/aio/_patch.py
azure/mgmt/trafficmanager/aio/_traffic_manager_management_client.py
azure/mgmt/trafficmanager/aio/operations/__init__.py
azure/mgmt/trafficmanager/aio/operations/_endpoints_operations.py
azure/mgmt/trafficmanager/aio/operations/_geographic_hierarchies_operations.py
azure/mgmt/trafficmanager/aio/operations/_heat_map_operations.py
azure/mgmt/trafficmanager/aio/operations/_profiles_operations.py
azure/mgmt/trafficmanager/aio/operations/_traffic_manager_user_metrics_keys_operations.py
azure/mgmt/trafficmanager/models/__init__.py
azure/mgmt/trafficmanager/models/_models_py3.py
azure/mgmt/trafficmanager/models/_traffic_manager_management_client_enums.py
azure/mgmt/trafficmanager/operations/__init__.py
azure/mgmt/trafficmanager/operations/_endpoints_operations.py
azure/mgmt/trafficmanager/operations/_geographic_hierarchies_operations.py
azure/mgmt/trafficmanager/operations/_heat_map_operations.py
azure/mgmt/trafficmanager/operations/_profiles_operations.py
azure/mgmt/trafficmanager/operations/_traffic_manager_user_metrics_keys_operations.py
azure_mgmt_trafficmanager-1.0.0.dist-info/LICENSE
azure_mgmt_trafficmanager-1.0.0.dist-info/METADATA
azure_mgmt_trafficmanager-1.0.0.dist-info/WHEEL
azure_mgmt_trafficmanager-1.0.0.dist-info/top_level.txt
azure_mgmt_trafficmanager-1.0.0.dist-info/RECORD
